huffmanfile-1.0.3.dist-info/RECORD
huffmanfile-1.0.3.dist-info/LICENSE
huffmanfile-1.0.3.dist-info/WHEEL
huffmanfile-1.0.3.dist-info/top_level.txt
huffmanfile-1.0.3.dist-info/METADATA
huffmanfile/_C.abi3.so
huffmanfile/__init__.py
huffmanfile/huffmanfile_test.py
huffmanfile/huffmanfile.py
