Metadata-Version: 2.1
Name: huffmanfile
Version: 1.0.3
Summary: Python bindings for libhuffman
Home-page: https://github.com/ybubnov/libhuffman
Author: Yasha Bubnov
Author-email: girokompass@gmail.com
Keywords: huffman,encoding,decoding,compression
Classifier: Development Status :: 3 - Alpha
Classifier: Intended Audience :: Developers
Classifier: Topic :: Software Development :: Libraries
Classifier: Topic :: System :: Archiving :: Compression
Classifier: Programming Language :: Python :: 3
Classifier: Programming Language :: Python :: 3.7
Classifier: Programming Language :: Python :: 3.8
Classifier: Programming Language :: Python :: 3.9
Classifier: Programming Language :: Python :: 3.10
Classifier: License :: OSI Approved :: Apache Software License
Classifier: License :: OSI Approved :: MIT License
License-File: LICENSE
Requires-Dist: cffi >=1.15.0
